{
  "did_you_mean": {"type": "text", "analyzer": "didYouMean"},
  "autocomplete": {"type": "text", "analyzer": "autocomplete"},

  "ID" : {"type" :"text", "fielddata": true },
  "Y": {"type" :"integer" },
  "MS" : {"type": "keyword", "index":true, "eager_global_ordinals": true},
  "VFN" : { "type" : "string", "analyzer" : "none" },
  "Mp" : {"type": "keyword", "index":true, "eager_global_ordinals": true},
  "Mh" : {"type": "keyword", "index":true, "eager_global_ordinals": true},
  "Man" : { "type" : "string",
            "analyzer" : "none"
        },
  "MMS" : { "type" : "string",
            "analyzer" : "none"
        },
  "TAN" : { "type" : "string", "analyzer" : "none" },
  "T" : { "type" : "string", "analyzer" : "none" },
  "Va" : { "type" : "string", "analyzer" : "none" },
  "Ve" : { "type" : "string", "analyzer" : "none" },
  "Mk" : { "type" : "string",
            "analyzer" : "none",
            "copy_to" : ["did_you_mean", "autocomplete"]
        },
  "Cn" : { "type": "keyword", "index":true, "eager_global_ordinals": true,
            "copy_to" : ["did_you_mean", "autocomplete"]
        },
  "Ct" : { "type" : "string", "analyzer" : "none" },
  "Cr" : { "type" : "string", "analyzer" : "none" },
  "r": {"type" :"integer" },
  "m__kg_": {"type" :"integer" },
  "Enedc__g_km_": {"type" :"integer" },
  "Ewltp__g_km_": {"type" :"integer" },
  "W__mm_": {"type" :"integer" },
  "At1__mm_": {"type" :"integer" },
  "At2__mm_": {"type" :"integer" },
  "Ft" : { "type" : "string", "analyzer" : "none" },
  "Fm" : { "type" : "string", "analyzer" : "none" },
  "ec__cm3_": {"type" :"integer" },
  "ep__KW_": {"type" :"integer" },
  "z__Wh_km_": {"type" :"integer" },
  "It" : { "type" : "string", "analyzer" : "none" },
  "Ernedc__g_km_" : {"type" :"double" },
  "Erwltp__g_km_" : {"type" :"double" },
  "De" : {"type" :"double" },
  "Vf": {"type" :"integer" },
  "Status" : {"type": "keyword", "index":true, "eager_global_ordinals": true},
  "date": {"type": "date","format": "yyyy-MM-dd"},
  "FtTrim": {"type": "keyword", "index":true, "eager_global_ordinals": true},
  "scStatus": {"type": "keyword", "index":true, "eager_global_ordinals": true},
  "year": {"type": "integer"},
  "Mt__kg_": {"type" :"integer" },
  "TPMLM__kg_": {"type" :"integer" },
  "Dam__kg_": {"type": "integer"},
  "Mf__kg_": {"type": "integer"}
}
